 play/asyncio_socket_open.py
 play/comms.py
 play/no_callback_registered.py
 play/no_pin_mode_set.py
archive/setup.py
archive/telemetrix_rpi_pico_w.py
examples/analog_input.py
examples/blink.py
examples/dht.py
examples/digital_input_pullup.py
examples/fade.py
examples/fade_with_range.py
examples/get_cpu_temperature.py
examples/get_pico_pins.py
examples/hc_sr04.py
examples/i2c_adxl345_accelerometer.py
examples/i2c_adxl345_accelerometer2.py
examples/loop_back.py
examples/neopixels.py
examples/servo.py
examples/spi_bme280.py
examples/spi_bme280_2.py
examples/stepper_absolute.py
examples/stepper_absolute2.py
examples/stepper_continuous.py
examples/stepper_relative.py
examples/stepper_run_speed_to_position.py
examples_aio/analog_input_aio.py
examples_aio/blink_aio.py
examples_aio/dht_aio.py
examples_aio/digital_input_pullup_aio.py
examples_aio/fade_aio.py
examples_aio/fade_with_range_aio.py
examples_aio/get_cpu_temperature_aio.py
examples_aio/get_pico_pins_aio.py
examples_aio/hc-sr04_aio.py
examples_aio/i2c_adxl345_accelerometer2_aio.py
examples_aio/i2c_adxl345_accelerometer_aio.py
examples_aio/loop_back_aio.py
examples_aio/neopixels_aio.py
examples_aio/servo_aio.py
examples_aio/spi_bme280_aio.py
examples_aio/spi_bme280_aio_2.py
examples_aio/stepper_absolute_aio.py
examples_aio/stepper_continuous_aio.py
examples_aio/stepper_relative_aio.py
telemetrix_rpi_pico_w/__init__.py
telemetrix_rpi_pico_w/private_constants.py
telemetrix_rpi_pico_w/telemetrix_rpi_pico_w.py
telemetrix_rpi_pico_w_aio/__init__.py
telemetrix_rpi_pico_w_aio/private_constants.py
telemetrix_rpi_pico_w_aio/telemetrix_pico_w_aio_socket.py
telemetrix_rpi_pico_w_aio/telemetrix_rpi_pico_w_aio.py
venv/bin/activate_this.py
venv2/bin/activate_this.py
telemetrix_rpi_pico_w-1.54.dist-info/METADATA
telemetrix_rpi_pico_w-1.54.dist-info/WHEEL
telemetrix_rpi_pico_w-1.54.dist-info/top_level.txt
telemetrix_rpi_pico_w-1.54.dist-info/RECORD
